{
	"public-main-offer": {
		"audience": {
			"bg": "",
			"cs": "",
			"de": "",
			"el": "",
			"en": "",
			"es": "",
			"fr": "",
			"he": "",
			"hr": "",
			"hu": "",
			"it": "",
			"nl": "",
			"pl": "",
			"pt": "",
			"ro": "",
			"sk": "",
			"sl": "",
			"ua": "публічна"
		},
		"question": {
			"bg": "",
			"cs": "",
			"de": "",
			"el": "",
			"en": "",
			"es": "",
			"fr": "",
			"he": "",
			"hr": "",
			"hu": "",
			"it": "",
			"nl": "",
			"pl": "",
			"pt": "",
			"ro": "",
			"sk": "",
			"sl": "",
			"ua": "Яка ваша основна пропозиція?"
		},
		"answer": {
			"bg": [],
			"cs": [],
			"de": [],
			"el": [],
			"en": [],
			"es": [],
			"fr": [],
			"he": [],
			"hr": [],
			"hu": [],
			"it": [],
			"nl": [],
			"pl": [],
			"pt": [],
			"ro": [],
			"sk": [],
			"sl": [],
			"ua": [
				"Ми створюємо готові до використання сайти для бізнесу та допомагаємо їм стати видимими в GPT і онлайн.",
				"Після цього пропонуємо передачу у власність і постійну підтримку."
			]
		}
	},
	"public-how-it-works": {
		"audience": {
			"bg": "",
			"cs": "",
			"de": "",
			"el": "",
			"en": "",
			"es": "",
			"fr": "",
			"he": "",
			"hr": "",
			"hu": "",
			"it": "",
			"nl": "",
			"pl": "",
			"pt": "",
			"ro": "",
			"sk": "",
			"sl": "",
			"ua": "публічна"
		},
		"question": {
			"bg": "",
			"cs": "",
			"de": "",
			"el": "",
			"en": "",
			"es": "",
			"fr": "",
			"he": "",
			"hr": "",
			"hu": "",
			"it": "",
			"nl": "",
			"pl": "",
			"pt": "",
			"ro": "",
			"sk": "",
			"sl": "",
			"ua": "Як це працює?"
		},
		"answer": {
			"bg": [],
			"cs": [],
			"de": [],
			"el": [],
			"en": [],
			"es": [],
			"fr": [],
			"he": [],
			"hr": [],
			"hu": [],
			"it": [],
			"nl": [],
			"pl": [],
			"pt": [],
			"ro": [],
			"sk": [],
			"sl": [],
			"ua": [
				"Ми готуємо готову концепцію сайту для вашого бізнесу.",
				"Ви переглядаєте її, обираєте формат підтримки, а ми запускаємо, обслуговуємо та покращуємо сайт разом із вами."
			]
		}
	},
	"public-what-is-included": {
		"audience": {
			"bg": "",
			"cs": "",
			"de": "",
			"el": "",
			"en": "",
			"es": "",
			"fr": "",
			"he": "",
			"hr": "",
			"hu": "",
			"it": "",
			"nl": "",
			"pl": "",
			"pt": "",
			"ro": "",
			"sk": "",
			"sl": "",
			"ua": "публічна"
		},
		"question": {
			"bg": "",
			"cs": "",
			"de": "",
			"el": "",
			"en": "",
			"es": "",
			"fr": "",
			"he": "",
			"hr": "",
			"hu": "",
			"it": "",
			"nl": "",
			"pl": "",
			"pt": "",
			"ro": "",
			"sk": "",
			"sl": "",
			"ua": "Що входить у підписку?"
		},
		"answer": {
			"bg": [],
			"cs": [],
			"de": [],
			"el": [],
			"en": [],
			"es": [],
			"fr": [],
			"he": [],
			"hr": [],
			"hu": [],
			"it": [],
			"nl": [],
			"pl": [],
			"pt": [],
			"ro": [],
			"sk": [],
			"sl": [],
			"ua": [
				"Хостинг.",
				"Обслуговування сайту.",
				"Виправлення помилок, якщо проблема є нашою відповідальністю."
			]
		}
	},
	"public-paid-request": {
		"audience": {
			"bg": "",
			"cs": "",
			"de": "",
			"el": "",
			"en": "",
			"es": "",
			"fr": "",
			"he": "",
			"hr": "",
			"hu": "",
			"it": "",
			"nl": "",
			"pl": "",
			"pt": "",
			"ro": "",
			"sk": "",
			"sl": "",
			"ua": "публічна"
		},
		"question": {
			"bg": "",
			"cs": "",
			"de": "",
			"el": "",
			"en": "",
			"es": "",
			"fr": "",
			"he": "",
			"hr": "",
			"hu": "",
			"it": "",
			"nl": "",
			"pl": "",
			"pt": "",
			"ro": "",
			"sk": "",
			"sl": "",
			"ua": "Що вважається платним запитом?"
		},
		"answer": {
			"bg": [],
			"cs": [],
			"de": [],
			"el": [],
			"en": [],
			"es": [],
			"fr": [],
			"he": [],
			"hr": [],
			"hu": [],
			"it": [],
			"nl": [],
			"pl": [],
			"pt": [],
			"ro": [],
			"sk": [],
			"sl": [],
			"ua": [
				"Будь-яка нова функція, редизайн або зміна поза початковою домовленістю вважається окремим платним запитом."
			]
		}
	},
	"public-bug-definition": {
		"audience": {
			"bg": "",
			"cs": "",
			"de": "",
			"el": "",
			"en": "",
			"es": "",
			"fr": "",
			"he": "",
			"hr": "",
			"hu": "",
			"it": "",
			"nl": "",
			"pl": "",
			"pt": "",
			"ro": "",
			"sk": "",
			"sl": "",
			"ua": "публічна"
		},
		"question": {
			"bg": "",
			"cs": "",
			"de": "",
			"el": "",
			"en": "",
			"es": "",
			"fr": "",
			"he": "",
			"hr": "",
			"hu": "",
			"it": "",
			"nl": "",
			"pl": "",
			"pt": "",
			"ro": "",
			"sk": "",
			"sl": "",
			"ua": "Що вважається помилкою?"
		},
		"answer": {
			"bg": [],
			"cs": [],
			"de": [],
			"el": [],
			"en": [],
			"es": [],
			"fr": [],
			"he": [],
			"hr": [],
			"hu": [],
			"it": [],
			"nl": [],
			"pl": [],
			"pt": [],
			"ro": [],
			"sk": [],
			"sl": [],
			"ua": [
				"Якщо щось не працює так, як було спочатку погоджено або описано, це вважається помилкою, і ми виправляємо її безкоштовно."
			]
		}
	},
	"public-content": {
		"audience": {
			"bg": "",
			"cs": "",
			"de": "",
			"el": "",
			"en": "",
			"es": "",
			"fr": "",
			"he": "",
			"hr": "",
			"hu": "",
			"it": "",
			"nl": "",
			"pl": "",
			"pt": "",
			"ro": "",
			"sk": "",
			"sl": "",
			"ua": "публічна"
		},
		"question": {
			"bg": "",
			"cs": "",
			"de": "",
			"el": "",
			"en": "",
			"es": "",
			"fr": "",
			"he": "",
			"hr": "",
			"hu": "",
			"it": "",
			"nl": "",
			"pl": "",
			"pt": "",
			"ro": "",
			"sk": "",
			"sl": "",
			"ua": "Ви надаєте тексти та зображення?"
		},
		"answer": {
			"bg": [],
			"cs": [],
			"de": [],
			"el": [],
			"en": [],
			"es": [],
			"fr": [],
			"he": [],
			"hr": [],
			"hu": [],
			"it": [],
			"nl": [],
			"pl": [],
			"pt": [],
			"ro": [],
			"sk": [],
			"sl": [],
			"ua": [
				"Ми використовуємо контент клієнта, якщо він є.",
				"За потреби можемо підготувати базовий стартовий контент для запуску."
			]
		}
	},
	"public-multilanguage": {
		"audience": {
			"bg": "",
			"cs": "",
			"de": "",
			"el": "",
			"en": "",
			"es": "",
			"fr": "",
			"he": "",
			"hr": "",
			"hu": "",
			"it": "",
			"nl": "",
			"pl": "",
			"pt": "",
			"ro": "",
			"sk": "",
			"sl": "",
			"ua": "публічна"
		},
		"question": {
			"bg": "",
			"cs": "",
			"de": "",
			"el": "",
			"en": "",
			"es": "",
			"fr": "",
			"he": "",
			"hr": "",
			"hu": "",
			"it": "",
			"nl": "",
			"pl": "",
			"pt": "",
			"ro": "",
			"sk": "",
			"sl": "",
			"ua": "Ви підтримуєте кілька мов?"
		},
		"answer": {
			"bg": [],
			"cs": [],
			"de": [],
			"el": [],
			"en": [],
			"es": [],
			"fr": [],
			"he": [],
			"hr": [],
			"hu": [],
			"it": [],
			"nl": [],
			"pl": [],
			"pt": [],
			"ro": [],
			"sk": [],
			"sl": [],
			"ua": [
				"Так. Багатомовна підтримка може бути включена за замовчуванням залежно від обсягу проєкту."
			]
		}
	},
	"public-ownership": {
		"audience": {
			"bg": "",
			"cs": "",
			"de": "",
			"el": "",
			"en": "",
			"es": "",
			"fr": "",
			"he": "",
			"hr": "",
			"hu": "",
			"it": "",
			"nl": "",
			"pl": "",
			"pt": "",
			"ro": "",
			"sk": "",
			"sl": "",
			"ua": "публічна"
		},
		"question": {
			"bg": "",
			"cs": "",
			"de": "",
			"el": "",
			"en": "",
			"es": "",
			"fr": "",
			"he": "",
			"hr": "",
			"hu": "",
			"it": "",
			"nl": "",
			"pl": "",
			"pt": "",
			"ro": "",
			"sk": "",
			"sl": "",
			"ua": "Кому належить сайт?"
		},
		"answer": {
			"bg": [],
			"cs": [],
			"de": [],
			"el": [],
			"en": [],
			"es": [],
			"fr": [],
			"he": [],
			"hr": [],
			"hu": [],
			"it": [],
			"nl": [],
			"pl": [],
			"pt": [],
			"ro": [],
			"sk": [],
			"sl": [],
			"ua": [
				"Це залежить від домовленості.",
				"Ми можемо передати повний репозиторій і домен або залишити проєкт на нашому боці та обслуговувати його для вас."
			]
		}
	},
	"public-take-website": {
		"audience": {
			"bg": "",
			"cs": "",
			"de": "",
			"el": "",
			"en": "",
			"es": "",
			"fr": "",
			"he": "",
			"hr": "",
			"hu": "",
			"it": "",
			"nl": "",
			"pl": "",
			"pt": "",
			"ro": "",
			"sk": "",
			"sl": "",
			"ua": "публічна"
		},
		"question": {
			"bg": "",
			"cs": "",
			"de": "",
			"el": "",
			"en": "",
			"es": "",
			"fr": "",
			"he": "",
			"hr": "",
			"hu": "",
			"it": "",
			"nl": "",
			"pl": "",
			"pt": "",
			"ro": "",
			"sk": "",
			"sl": "",
			"ua": "Чи можу я піти й забрати сайт із собою?"
		},
		"answer": {
			"bg": [],
			"cs": [],
			"de": [],
			"el": [],
			"en": [],
			"es": [],
			"fr": [],
			"he": [],
			"hr": [],
			"hu": [],
			"it": [],
			"nl": [],
			"pl": [],
			"pt": [],
			"ro": [],
			"sk": [],
			"sl": [],
			"ua": [
				"Так. Кожен проєкт є незалежним і може бути переданий згідно з домовленістю."
			]
		}
	},
	"public-hosting": {
		"audience": {
			"bg": "",
			"cs": "",
			"de": "",
			"el": "",
			"en": "",
			"es": "",
			"fr": "",
			"he": "",
			"hr": "",
			"hu": "",
			"it": "",
			"nl": "",
			"pl": "",
			"pt": "",
			"ro": "",
			"sk": "",
			"sl": "",
			"ua": "публічна"
		},
		"question": {
			"bg": "",
			"cs": "",
			"de": "",
			"el": "",
			"en": "",
			"es": "",
			"fr": "",
			"he": "",
			"hr": "",
			"hu": "",
			"it": "",
			"nl": "",
			"pl": "",
			"pt": "",
			"ro": "",
			"sk": "",
			"sl": "",
			"ua": "Де розміщуються сайти?"
		},
		"answer": {
			"bg": [],
			"cs": [],
			"de": [],
			"el": [],
			"en": [],
			"es": [],
			"fr": [],
			"he": [],
			"hr": [],
			"hu": [],
			"it": [],
			"nl": [],
			"pl": [],
			"pt": [],
			"ro": [],
			"sk": [],
			"sl": [],
			"ua": [
				"Проєкти можуть розміщуватися на GitHub Pages або в іншого провайдера, якого обере клієнт."
			]
		}
	},
	"public-client-stop-paying": {
		"audience": {
			"bg": "",
			"cs": "",
			"de": "",
			"el": "",
			"en": "",
			"es": "",
			"fr": "",
			"he": "",
			"hr": "",
			"hu": "",
			"it": "",
			"nl": "",
			"pl": "",
			"pt": "",
			"ro": "",
			"sk": "",
			"sl": "",
			"ua": "публічна"
		},
		"question": {
			"bg": "",
			"cs": "",
			"de": "",
			"el": "",
			"en": "",
			"es": "",
			"fr": "",
			"he": "",
			"hr": "",
			"hu": "",
			"it": "",
			"nl": "",
			"pl": "",
			"pt": "",
			"ro": "",
			"sk": "",
			"sl": "",
			"ua": "Що станеться, якщо я перестану платити?"
		},
		"answer": {
			"bg": [],
			"cs": [],
			"de": [],
			"el": [],
			"en": [],
			"es": [],
			"fr": [],
			"he": [],
			"hr": [],
			"hu": [],
			"it": [],
			"nl": [],
			"pl": [],
			"pt": [],
			"ro": [],
			"sk": [],
			"sl": [],
			"ua": [
				"Сайт може залишатися доступним, але адміністративний доступ може бути обмеженим або лише для перегляду залежно від угоди про підтримку."
			]
		}
	},
	"public-change-requirements": {
		"audience": {
			"bg": "",
			"cs": "",
			"de": "",
			"el": "",
			"en": "",
			"es": "",
			"fr": "",
			"he": "",
			"hr": "",
			"hu": "",
			"it": "",
			"nl": "",
			"pl": "",
			"pt": "",
			"ro": "",
			"sk": "",
			"sl": "",
			"ua": "публічна"
		},
		"question": {
			"bg": "",
			"cs": "",
			"de": "",
			"el": "",
			"en": "",
			"es": "",
			"fr": "",
			"he": "",
			"hr": "",
			"hu": "",
			"it": "",
			"nl": "",
			"pl": "",
			"pt": "",
			"ro": "",
			"sk": "",
			"sl": "",
			"ua": "Що буде, якщо я зміню вимоги під час розробки?"
		},
		"answer": {
			"bg": [],
			"cs": [],
			"de": [],
			"el": [],
			"en": [],
			"es": [],
			"fr": [],
			"he": [],
			"hr": [],
			"hu": [],
			"it": [],
			"nl": [],
			"pl": [],
			"pt": [],
			"ro": [],
			"sk": [],
			"sl": [],
			"ua": [
				"Розробка призупиняється.",
				"Запит оцінюється повторно.",
				"Ми продовжуємо лише після затвердження оновленого обсягу робіт і ціни."
			]
		}
	},
	"public-multiple-requests": {
		"audience": {
			"bg": "",
			"cs": "",
			"de": "",
			"el": "",
			"en": "",
			"es": "",
			"fr": "",
			"he": "",
			"hr": "",
			"hu": "",
			"it": "",
			"nl": "",
			"pl": "",
			"pt": "",
			"ro": "",
			"sk": "",
			"sl": "",
			"ua": "публічна"
		},
		"question": {
			"bg": "",
			"cs": "",
			"de": "",
			"el": "",
			"en": "",
			"es": "",
			"fr": "",
			"he": "",
			"hr": "",
			"hu": "",
			"it": "",
			"nl": "",
			"pl": "",
			"pt": "",
			"ro": "",
			"sk": "",
			"sl": "",
			"ua": "Чи можу я подати кілька запитів?"
		},
		"answer": {
			"bg": [],
			"cs": [],
			"de": [],
			"el": [],
			"en": [],
			"es": [],
			"fr": [],
			"he": [],
			"hr": [],
			"hu": [],
			"it": [],
			"nl": [],
			"pl": [],
			"pt": [],
			"ro": [],
			"sk": [],
			"sl": [],
			"ua": [
				"Так.",
				"Кожен запит має власну оцінку, позицію в черзі та очікуваний час початку."
			]
		}
	},
	"public-approval": {
		"audience": {
			"bg": "",
			"cs": "",
			"de": "",
			"el": "",
			"en": "",
			"es": "",
			"fr": "",
			"he": "",
			"hr": "",
			"hu": "",
			"it": "",
			"nl": "",
			"pl": "",
			"pt": "",
			"ro": "",
			"sk": "",
			"sl": "",
			"ua": "публічна"
		},
		"question": {
			"bg": "",
			"cs": "",
			"de": "",
			"el": "",
			"en": "",
			"es": "",
			"fr": "",
			"he": "",
			"hr": "",
			"hu": "",
			"it": "",
			"nl": "",
			"pl": "",
			"pt": "",
			"ro": "",
			"sk": "",
			"sl": "",
			"ua": "Як затверджується виконана робота?"
		},
		"answer": {
			"bg": [],
			"cs": [],
			"de": [],
			"el": [],
			"en": [],
			"es": [],
			"fr": [],
			"he": [],
			"hr": [],
			"hu": [],
			"it": [],
			"nl": [],
			"pl": [],
			"pt": [],
			"ro": [],
			"sk": [],
			"sl": [],
			"ua": [
				"Звичайний процес такий: розробник завершує завдання, агент перевіряє його, а клієнт дає фінальне затвердження."
			]
		}
	},
	"public-no-response": {
		"audience": {
			"bg": "",
			"cs": "",
			"de": "",
			"el": "",
			"en": "",
			"es": "",
			"fr": "",
			"he": "",
			"hr": "",
			"hu": "",
			"it": "",
			"nl": "",
			"pl": "",
			"pt": "",
			"ro": "",
			"sk": "",
			"sl": "",
			"ua": "публічна"
		},
		"question": {
			"bg": "",
			"cs": "",
			"de": "",
			"el": "",
			"en": "",
			"es": "",
			"fr": "",
			"he": "",
			"hr": "",
			"hu": "",
			"it": "",
			"nl": "",
			"pl": "",
			"pt": "",
			"ro": "",
			"sk": "",
			"sl": "",
			"ua": "Що буде, якщо я не відповім після завершення?"
		},
		"answer": {
			"bg": [],
			"cs": [],
			"de": [],
			"el": [],
			"en": [],
			"es": [],
			"fr": [],
			"he": [],
			"hr": [],
			"hu": [],
			"it": [],
			"nl": [],
			"pl": [],
			"pt": [],
			"ro": [],
			"sk": [],
			"sl": [],
			"ua": [
				"Якщо робота вже оплачена й передана, завдання залишається завершеним і очікує вашого підтвердження."
			]
		}
	},
	"public-main-advantage": {
		"audience": {
			"bg": "",
			"cs": "",
			"de": "",
			"el": "",
			"en": "",
			"es": "",
			"fr": "",
			"he": "",
			"hr": "",
			"hu": "",
			"it": "",
			"nl": "",
			"pl": "",
			"pt": "",
			"ro": "",
			"sk": "",
			"sl": "",
			"ua": "публічна"
		},
		"question": {
			"bg": "",
			"cs": "",
			"de": "",
			"el": "",
			"en": "",
			"es": "",
			"fr": "",
			"he": "",
			"hr": "",
			"hu": "",
			"it": "",
			"nl": "",
			"pl": "",
			"pt": "",
			"ro": "",
			"sk": "",
			"sl": "",
			"ua": "У чому ваша головна перевага?"
		},
		"answer": {
			"bg": [],
			"cs": [],
			"de": [],
			"el": [],
			"en": [],
			"es": [],
			"fr": [],
			"he": [],
			"hr": [],
			"hu": [],
			"it": [],
			"nl": [],
			"pl": [],
			"pt": [],
			"ro": [],
			"sk": [],
			"sl": [],
			"ua": [
				"Ми спочатку створюємо, а потім продаємо.",
				"Ви працюєте зі справжніми розробниками, а не лише з конструкторами без коду.",
				"Ви отримуєте швидший запуск і постійну підтримку."
			]
		}
	},
	"public-gpt-visibility": {
		"audience": {
			"bg": "",
			"cs": "",
			"de": "",
			"el": "",
			"en": "",
			"es": "",
			"fr": "",
			"he": "",
			"hr": "",
			"hu": "",
			"it": "",
			"nl": "",
			"pl": "",
			"pt": "",
			"ro": "",
			"sk": "",
			"sl": "",
			"ua": "публічна"
		},
		"question": {
			"bg": "",
			"cs": "",
			"de": "",
			"el": "",
			"en": "",
			"es": "",
			"fr": "",
			"he": "",
			"hr": "",
			"hu": "",
			"it": "",
			"nl": "",
			"pl": "",
			"pt": "",
			"ro": "",
			"sk": "",
			"sl": "",
			"ua": "Як сайт може допомогти моєму бізнесу з’являтися в GPT?"
		},
		"answer": {
			"bg": [],
			"cs": [],
			"de": [],
			"el": [],
			"en": [],
			"es": [],
			"fr": [],
			"he": [],
			"hr": [],
			"hu": [],
			"it": [],
			"nl": [],
			"pl": [],
			"pt": [],
			"ro": [],
			"sk": [],
			"sl": [],
			"ua": [
				"Зрозумілий публічний сайт покращує вашу присутність онлайн і допомагає AI-системам краще розуміти ваш бізнес.",
				"Структурована інформація, описи послуг, контактні дані та публічна видимість допомагають цьому."
			]
		}
	},
	"public-support-speed": {
		"audience": {
			"bg": "",
			"cs": "",
			"de": "",
			"el": "",
			"en": "",
			"es": "",
			"fr": "",
			"he": "",
			"hr": "",
			"hu": "",
			"it": "",
			"nl": "",
			"pl": "",
			"pt": "",
			"ro": "",
			"sk": "",
			"sl": "",
			"ua": "публічна"
		},
		"question": {
			"bg": "",
			"cs": "",
			"de": "",
			"el": "",
			"en": "",
			"es": "",
			"fr": "",
			"he": "",
			"hr": "",
			"hu": "",
			"it": "",
			"nl": "",
			"pl": "",
			"pt": "",
			"ro": "",
			"sk": "",
			"sl": "",
			"ua": "Як швидко ви обробляєте нові запити?"
		},
		"answer": {
			"bg": [],
			"cs": [],
			"de": [],
			"el": [],
			"en": [],
			"es": [],
			"fr": [],
			"he": [],
			"hr": [],
			"hu": [],
			"it": [],
			"nl": [],
			"pl": [],
			"pt": [],
			"ro": [],
			"sk": [],
			"sl": [],
			"ua": [
				"Терміни залежать від черги та розміру запиту.",
				"Кожен запит отримує оцінку та очікуваний час початку."
			]
		}
	},
	"agent-main-offer": {
		"audience": {
			"bg": "",
			"cs": "",
			"de": "",
			"el": "",
			"en": "",
			"es": "",
			"fr": "",
			"he": "",
			"hr": "",
			"hu": "",
			"it": "",
			"nl": "",
			"pl": "",
			"pt": "",
			"ro": "",
			"sk": "",
			"sl": "",
			"ua": "агент"
		},
		"question": {
			"bg": "",
			"cs": "",
			"de": "",
			"el": "",
			"en": "",
			"es": "",
			"fr": "",
			"he": "",
			"hr": "",
			"hu": "",
			"it": "",
			"nl": "",
			"pl": "",
			"pt": "",
			"ro": "",
			"sk": "",
			"sl": "",
			"ua": "Яка наша основна пропозиція?"
		},
		"answer": {
			"bg": [],
			"cs": [],
			"de": [],
			"el": [],
			"en": [],
			"es": [],
			"fr": [],
			"he": [],
			"hr": [],
			"hu": [],
			"it": [],
			"nl": [],
			"pl": [],
			"pt": [],
			"ro": [],
			"sk": [],
			"sl": [],
			"ua": [
				"Ми створюємо готові до використання сайти для бізнесу та допомагаємо їм стати видимими в GPT і онлайн.",
				"Після цього пропонуємо передачу у власність і постійну підтримку."
			]
		}
	},
	"agent-first-message": {
		"audience": {
			"bg": "",
			"cs": "",
			"de": "",
			"el": "",
			"en": "",
			"es": "",
			"fr": "",
			"he": "",
			"hr": "",
			"hu": "",
			"it": "",
			"nl": "",
			"pl": "",
			"pt": "",
			"ro": "",
			"sk": "",
			"sl": "",
			"ua": "агент"
		},
		"question": {
			"bg": "",
			"cs": "",
			"de": "",
			"el": "",
			"en": "",
			"es": "",
			"fr": "",
			"he": "",
			"hr": "",
			"hu": "",
			"it": "",
			"nl": "",
			"pl": "",
			"pt": "",
			"ro": "",
			"sk": "",
			"sl": "",
			"ua": "Що мені спочатку сказати бізнесу?"
		},
		"answer": {
			"bg": [],
			"cs": [],
			"de": [],
			"el": [],
			"en": [],
			"es": [],
			"fr": [],
			"he": [],
			"hr": [],
			"hu": [],
			"it": [],
			"nl": [],
			"pl": [],
			"pt": [],
			"ro": [],
			"sk": [],
			"sl": [],
			"ua": [
				"Люди вже шукають у GPT - ми зробили ваш бізнес видимим там. Хочете подивитися?"
			]
		}
	},
	"agent-verify-owner": {
		"audience": {
			"bg": "",
			"cs": "",
			"de": "",
			"el": "",
			"en": "",
			"es": "",
			"fr": "",
			"he": "",
			"hr": "",
			"hu": "",
			"it": "",
			"nl": "",
			"pl": "",
			"pt": "",
			"ro": "",
			"sk": "",
			"sl": "",
			"ua": "агент"
		},
		"question": {
			"bg": "",
			"cs": "",
			"de": "",
			"el": "",
			"en": "",
			"es": "",
			"fr": "",
			"he": "",
			"hr": "",
			"hu": "",
			"it": "",
			"nl": "",
			"pl": "",
			"pt": "",
			"ro": "",
			"sk": "",
			"sl": "",
			"ua": "Як ми перевіряємо власника бізнесу?"
		},
		"answer": {
			"bg": [],
			"cs": [],
			"de": [],
			"el": [],
			"en": [],
			"es": [],
			"fr": [],
			"he": [],
			"hr": [],
			"hu": [],
			"it": [],
			"nl": [],
			"pl": [],
			"pt": [],
			"ro": [],
			"sk": [],
			"sl": [],
			"ua": [
				"Ми фізично приходимо на локацію, просимо адміністратора або власника й презентуємо продукт напряму."
			]
		}
	},
	"agent-show-client": {
		"audience": {
			"bg": "",
			"cs": "",
			"de": "",
			"el": "",
			"en": "",
			"es": "",
			"fr": "",
			"he": "",
			"hr": "",
			"hu": "",
			"it": "",
			"nl": "",
			"pl": "",
			"pt": "",
			"ro": "",
			"sk": "",
			"sl": "",
			"ua": "агент"
		},
		"question": {
			"bg": "",
			"cs": "",
			"de": "",
			"el": "",
			"en": "",
			"es": "",
			"fr": "",
			"he": "",
			"hr": "",
			"hu": "",
			"it": "",
			"nl": "",
			"pl": "",
			"pt": "",
			"ro": "",
			"sk": "",
			"sl": "",
			"ua": "Що ми показуємо клієнту?"
		},
		"answer": {
			"bg": [],
			"cs": [],
			"de": [],
			"el": [],
			"en": [],
			"es": [],
			"fr": [],
			"he": [],
			"hr": [],
			"hu": [],
			"it": [],
			"nl": [],
			"pl": [],
			"pt": [],
			"ro": [],
			"sk": [],
			"sl": [],
			"ua": [
				"Готовий сайт.",
				"Демо адміністративної панелі, якщо потрібно.",
				"Пояснення, як це допомагає отримувати клієнтів."
			]
		}
	},
	"agent-if-client-wants": {
		"audience": {
			"bg": "",
			"cs": "",
			"de": "",
			"el": "",
			"en": "",
			"es": "",
			"fr": "",
			"he": "",
			"hr": "",
			"hu": "",
			"it": "",
			"nl": "",
			"pl": "",
			"pt": "",
			"ro": "",
			"sk": "",
			"sl": "",
			"ua": "агент"
		},
		"question": {
			"bg": "",
			"cs": "",
			"de": "",
			"el": "",
			"en": "",
			"es": "",
			"fr": "",
			"he": "",
			"hr": "",
			"hu": "",
			"it": "",
			"nl": "",
			"pl": "",
			"pt": "",
			"ro": "",
			"sk": "",
			"sl": "",
			"ua": "Що відбувається, якщо вони хочуть це отримати?"
		},
		"answer": {
			"bg": [],
			"cs": [],
			"de": [],
			"el": [],
			"en": [],
			"es": [],
			"fr": [],
			"he": [],
			"hr": [],
			"hu": [],
			"it": [],
			"nl": [],
			"pl": [],
			"pt": [],
			"ro": [],
			"sk": [],
			"sl": [],
			"ua": [
				"Вони запитують право власності.",
				"Ми надаємо варіанти ціни.",
				"Вони обирають план.",
				"Вони отримують доступ після оплати."
			]
		}
	},
	"agent-what-clients-pay-for": {
		"audience": {
			"bg": "",
			"cs": "",
			"de": "",
			"el": "",
			"en": "",
			"es": "",
			"fr": "",
			"he": "",
			"hr": "",
			"hu": "",
			"it": "",
			"nl": "",
			"pl": "",
			"pt": "",
			"ro": "",
			"sk": "",
			"sl": "",
			"ua": "агент"
		},
		"question": {
			"bg": "",
			"cs": "",
			"de": "",
			"el": "",
			"en": "",
			"es": "",
			"fr": "",
			"he": "",
			"hr": "",
			"hu": "",
			"it": "",
			"nl": "",
			"pl": "",
			"pt": "",
			"ro": "",
			"sk": "",
			"sl": "",
			"ua": "За що платять клієнти?"
		},
		"answer": {
			"bg": [],
			"cs": [],
			"de": [],
			"el": [],
			"en": [],
			"es": [],
			"fr": [],
			"he": [],
			"hr": [],
			"hu": [],
			"it": [],
			"nl": [],
			"pl": [],
			"pt": [],
			"ro": [],
			"sk": [],
			"sl": [],
			"ua": [
				"Щомісячна підписка за хостинг і обслуговування.",
				"Додаткові функції оцінюються й оплачуються окремо."
			]
		}
	},
	"agent-subscription-includes": {
		"audience": {
			"bg": "",
			"cs": "",
			"de": "",
			"el": "",
			"en": "",
			"es": "",
			"fr": "",
			"he": "",
			"hr": "",
			"hu": "",
			"it": "",
			"nl": "",
			"pl": "",
			"pt": "",
			"ro": "",
			"sk": "",
			"sl": "",
			"ua": "агент"
		},
		"question": {
			"bg": "",
			"cs": "",
			"de": "",
			"el": "",
			"en": "",
			"es": "",
			"fr": "",
			"he": "",
			"hr": "",
			"hu": "",
			"it": "",
			"nl": "",
			"pl": "",
			"pt": "",
			"ro": "",
			"sk": "",
			"sl": "",
			"ua": "Що входить у підписку?"
		},
		"answer": {
			"bg": [],
			"cs": [],
			"de": [],
			"el": [],
			"en": [],
			"es": [],
			"fr": [],
			"he": [],
			"hr": [],
			"hu": [],
			"it": [],
			"nl": [],
			"pl": [],
			"pt": [],
			"ro": [],
			"sk": [],
			"sl": [],
			"ua": [
				"Хостинг.",
				"Виправлення помилок, якщо це наша відповідальність.",
				"Обслуговування сайту."
			]
		}
	},
	"agent-bug-definition": {
		"audience": {
			"bg": "",
			"cs": "",
			"de": "",
			"el": "",
			"en": "",
			"es": "",
			"fr": "",
			"he": "",
			"hr": "",
			"hu": "",
			"it": "",
			"nl": "",
			"pl": "",
			"pt": "",
			"ro": "",
			"sk": "",
			"sl": "",
			"ua": "агент"
		},
		"question": {
			"bg": "",
			"cs": "",
			"de": "",
			"el": "",
			"en": "",
			"es": "",
			"fr": "",
			"he": "",
			"hr": "",
			"hu": "",
			"it": "",
			"nl": "",
			"pl": "",
			"pt": "",
			"ro": "",
			"sk": "",
			"sl": "",
			"ua": "Що вважається помилкою?"
		},
		"answer": {
			"bg": [],
			"cs": [],
			"de": [],
			"el": [],
			"en": [],
			"es": [],
			"fr": [],
			"he": [],
			"hr": [],
			"hu": [],
			"it": [],
			"nl": [],
			"pl": [],
			"pt": [],
			"ro": [],
			"sk": [],
			"sl": [],
			"ua": [
				"Якщо щось не працює так, як було спочатку погоджено або описано, це помилка, і ми виправляємо її безкоштовно."
			]
		}
	},
	"agent-paid-request": {
		"audience": {
			"bg": "",
			"cs": "",
			"de": "",
			"el": "",
			"en": "",
			"es": "",
			"fr": "",
			"he": "",
			"hr": "",
			"hu": "",
			"it": "",
			"nl": "",
			"pl": "",
			"pt": "",
			"ro": "",
			"sk": "",
			"sl": "",
			"ua": "агент"
		},
		"question": {
			"bg": "",
			"cs": "",
			"de": "",
			"el": "",
			"en": "",
			"es": "",
			"fr": "",
			"he": "",
			"hr": "",
			"hu": "",
			"it": "",
			"nl": "",
			"pl": "",
			"pt": "",
			"ro": "",
			"sk": "",
			"sl": "",
			"ua": "Що вважається платним запитом?"
		},
		"answer": {
			"bg": [],
			"cs": [],
			"de": [],
			"el": [],
			"en": [],
			"es": [],
			"fr": [],
			"he": [],
			"hr": [],
			"hu": [],
			"it": [],
			"nl": [],
			"pl": [],
			"pt": [],
			"ro": [],
			"sk": [],
			"sl": [],
			"ua": [
				"Будь-яка нова функція або зміна поза початковою домовленістю."
			]
		}
	},
	"agent-change-requirements": {
		"audience": {
			"bg": "",
			"cs": "",
			"de": "",
			"el": "",
			"en": "",
			"es": "",
			"fr": "",
			"he": "",
			"hr": "",
			"hu": "",
			"it": "",
			"nl": "",
			"pl": "",
			"pt": "",
			"ro": "",
			"sk": "",
			"sl": "",
			"ua": "агент"
		},
		"question": {
			"bg": "",
			"cs": "",
			"de": "",
			"el": "",
			"en": "",
			"es": "",
			"fr": "",
			"he": "",
			"hr": "",
			"hu": "",
			"it": "",
			"nl": "",
			"pl": "",
			"pt": "",
			"ro": "",
			"sk": "",
			"sl": "",
			"ua": "Що робити, якщо клієнт змінює вимоги під час розробки?"
		},
		"answer": {
			"bg": [],
			"cs": [],
			"de": [],
			"el": [],
			"en": [],
			"es": [],
			"fr": [],
			"he": [],
			"hr": [],
			"hu": [],
			"it": [],
			"nl": [],
			"pl": [],
			"pt": [],
			"ro": [],
			"sk": [],
			"sl": [],
			"ua": [
				"Розробка призупиняється.",
				"Запит оцінюється повторно.",
				"Клієнт має затвердити нову ціну перед продовженням роботи."
			]
		}
	},
	"agent-multiple-requests": {
		"audience": {
			"bg": "",
			"cs": "",
			"de": "",
			"el": "",
			"en": "",
			"es": "",
			"fr": "",
			"he": "",
			"hr": "",
			"hu": "",
			"it": "",
			"nl": "",
			"pl": "",
			"pt": "",
			"ro": "",
			"sk": "",
			"sl": "",
			"ua": "агент"
		},
		"question": {
			"bg": "",
			"cs": "",
			"de": "",
			"el": "",
			"en": "",
			"es": "",
			"fr": "",
			"he": "",
			"hr": "",
			"hu": "",
			"it": "",
			"nl": "",
			"pl": "",
			"pt": "",
			"ro": "",
			"sk": "",
			"sl": "",
			"ua": "Чи можуть клієнти мати кілька запитів?"
		},
		"answer": {
			"bg": [],
			"cs": [],
			"de": [],
			"el": [],
			"en": [],
			"es": [],
			"fr": [],
			"he": [],
			"hr": [],
			"hu": [],
			"it": [],
			"nl": [],
			"pl": [],
			"pt": [],
			"ro": [],
			"sk": [],
			"sl": [],
			"ua": [
				"Так.",
				"Кожен запит має власну ціну, позицію в черзі та приблизний час початку."
			]
		}
	},
	"agent-delays": {
		"audience": {
			"bg": "",
			"cs": "",
			"de": "",
			"el": "",
			"en": "",
			"es": "",
			"fr": "",
			"he": "",
			"hr": "",
			"hu": "",
			"it": "",
			"nl": "",
			"pl": "",
			"pt": "",
			"ro": "",
			"sk": "",
			"sl": "",
			"ua": "агент"
		},
		"question": {
			"bg": "",
			"cs": "",
			"de": "",
			"el": "",
			"en": "",
			"es": "",
			"fr": "",
			"he": "",
			"hr": "",
			"hu": "",
			"it": "",
			"nl": "",
			"pl": "",
			"pt": "",
			"ro": "",
			"sk": "",
			"sl": "",
			"ua": "Як ми працюємо із затримками або помилками в оцінці?"
		},
		"answer": {
			"bg": [],
			"cs": [],
			"de": [],
			"el": [],
			"en": [],
			"es": [],
			"fr": [],
			"he": [],
			"hr": [],
			"hu": [],
			"it": [],
			"nl": [],
			"pl": [],
			"pt": [],
			"ro": [],
			"sk": [],
			"sl": [],
			"ua": [
				"Ми комунікуємо з клієнтом.",
				"Ми або коригуємо терміни, або скасовуємо роботу й повертаємо кошти за потреби."
			]
		}
	},
	"agent-task-done": {
		"audience": {
			"bg": "",
			"cs": "",
			"de": "",
			"el": "",
			"en": "",
			"es": "",
			"fr": "",
			"he": "",
			"hr": "",
			"hu": "",
			"it": "",
			"nl": "",
			"pl": "",
			"pt": "",
			"ro": "",
			"sk": "",
			"sl": "",
			"ua": "агент"
		},
		"question": {
			"bg": "",
			"cs": "",
			"de": "",
			"el": "",
			"en": "",
			"es": "",
			"fr": "",
			"he": "",
			"hr": "",
			"hu": "",
			"it": "",
			"nl": "",
			"pl": "",
			"pt": "",
			"ro": "",
			"sk": "",
			"sl": "",
			"ua": "Хто вирішує, коли завдання виконано?"
		},
		"answer": {
			"bg": [],
			"cs": [],
			"de": [],
			"el": [],
			"en": [],
			"es": [],
			"fr": [],
			"he": [],
			"hr": [],
			"hu": [],
			"it": [],
			"nl": [],
			"pl": [],
			"pt": [],
			"ro": [],
			"sk": [],
			"sl": [],
			"ua": [
				"Розробник позначає завдання виконаним.",
				"Агент перевіряє й позначає його виконаним.",
				"Клієнт дає фінальне затвердження."
			]
		}
	},
	"agent-client-no-response": {
		"audience": {
			"bg": "",
			"cs": "",
			"de": "",
			"el": "",
			"en": "",
			"es": "",
			"fr": "",
			"he": "",
			"hr": "",
			"hu": "",
			"it": "",
			"nl": "",
			"pl": "",
			"pt": "",
			"ro": "",
			"sk": "",
			"sl": "",
			"ua": "агент"
		},
		"question": {
			"bg": "",
			"cs": "",
			"de": "",
			"el": "",
			"en": "",
			"es": "",
			"fr": "",
			"he": "",
			"hr": "",
			"hu": "",
			"it": "",
			"nl": "",
			"pl": "",
			"pt": "",
			"ro": "",
			"sk": "",
			"sl": "",
			"ua": "Що, якщо клієнт не відповідає після завершення?"
		},
		"answer": {
			"bg": [],
			"cs": [],
			"de": [],
			"el": [],
			"en": [],
			"es": [],
			"fr": [],
			"he": [],
			"hr": [],
			"hu": [],
			"it": [],
			"nl": [],
			"pl": [],
			"pt": [],
			"ro": [],
			"sk": [],
			"sl": [],
			"ua": [
				"Якщо робота вже оплачена, проєкт залишається завершеним і очікує затвердження."
			]
		}
	},
	"agent-stop-paying": {
		"audience": {
			"bg": "",
			"cs": "",
			"de": "",
			"el": "",
			"en": "",
			"es": "",
			"fr": "",
			"he": "",
			"hr": "",
			"hu": "",
			"it": "",
			"nl": "",
			"pl": "",
			"pt": "",
			"ro": "",
			"sk": "",
			"sl": "",
			"ua": "агент"
		},
		"question": {
			"bg": "",
			"cs": "",
			"de": "",
			"el": "",
			"en": "",
			"es": "",
			"fr": "",
			"he": "",
			"hr": "",
			"hu": "",
			"it": "",
			"nl": "",
			"pl": "",
			"pt": "",
			"ro": "",
			"sk": "",
			"sl": "",
			"ua": "Що буде, якщо клієнт перестане платити?"
		},
		"answer": {
			"bg": [],
			"cs": [],
			"de": [],
			"el": [],
			"en": [],
			"es": [],
			"fr": [],
			"he": [],
			"hr": [],
			"hu": [],
			"it": [],
			"nl": [],
			"pl": [],
			"pt": [],
			"ro": [],
			"sk": [],
			"sl": [],
			"ua": [
				"Сайт залишається доступним, але адміністративний доступ стає доступом лише для перегляду."
			]
		}
	},
	"agent-website-owner": {
		"audience": {
			"bg": "",
			"cs": "",
			"de": "",
			"el": "",
			"en": "",
			"es": "",
			"fr": "",
			"he": "",
			"hr": "",
			"hu": "",
			"it": "",
			"nl": "",
			"pl": "",
			"pt": "",
			"ro": "",
			"sk": "",
			"sl": "",
			"ua": "агент"
		},
		"question": {
			"bg": "",
			"cs": "",
			"de": "",
			"el": "",
			"en": "",
			"es": "",
			"fr": "",
			"he": "",
			"hr": "",
			"hu": "",
			"it": "",
			"nl": "",
			"pl": "",
			"pt": "",
			"ro": "",
			"sk": "",
			"sl": "",
			"ua": "Кому належить сайт?"
		},
		"answer": {
			"bg": [],
			"cs": [],
			"de": [],
			"el": [],
			"en": [],
			"es": [],
			"fr": [],
			"he": [],
			"hr": [],
			"hu": [],
			"it": [],
			"nl": [],
			"pl": [],
			"pt": [],
			"ro": [],
			"sk": [],
			"sl": [],
			"ua": [
				"Це залежить від домовленості.",
				"Ми можемо передати повний репозиторій і домен або залишити його на нашому боці та обслуговувати."
			]
		}
	},
	"agent-hosting": {
		"audience": {
			"bg": "",
			"cs": "",
			"de": "",
			"el": "",
			"en": "",
			"es": "",
			"fr": "",
			"he": "",
			"hr": "",
			"hu": "",
			"it": "",
			"nl": "",
			"pl": "",
			"pt": "",
			"ro": "",
			"sk": "",
			"sl": "",
			"ua": "агент"
		},
		"question": {
			"bg": "",
			"cs": "",
			"de": "",
			"el": "",
			"en": "",
			"es": "",
			"fr": "",
			"he": "",
			"hr": "",
			"hu": "",
			"it": "",
			"nl": "",
			"pl": "",
			"pt": "",
			"ro": "",
			"sk": "",
			"sl": "",
			"ua": "Де розміщуються сайти?"
		},
		"answer": {
			"bg": [],
			"cs": [],
			"de": [],
			"el": [],
			"en": [],
			"es": [],
			"fr": [],
			"he": [],
			"hr": [],
			"hu": [],
			"it": [],
			"nl": [],
			"pl": [],
			"pt": [],
			"ro": [],
			"sk": [],
			"sl": [],
			"ua": [
				"Зараз проєкти можуть розміщуватися на GitHub Pages.",
				"Пізніше їх можна перенести до будь-якого провайдера, якого обере клієнт."
			]
		}
	},
	"agent-transfer": {
		"audience": {
			"bg": "",
			"cs": "",
			"de": "",
			"el": "",
			"en": "",
			"es": "",
			"fr": "",
			"he": "",
			"hr": "",
			"hu": "",
			"it": "",
			"nl": "",
			"pl": "",
			"pt": "",
			"ro": "",
			"sk": "",
			"sl": "",
			"ua": "агент"
		},
		"question": {
			"bg": "",
			"cs": "",
			"de": "",
			"el": "",
			"en": "",
			"es": "",
			"fr": "",
			"he": "",
			"hr": "",
			"hu": "",
			"it": "",
			"nl": "",
			"pl": "",
			"pt": "",
			"ro": "",
			"sk": "",
			"sl": "",
			"ua": "Чи може клієнт піти й забрати сайт?"
		},
		"answer": {
			"bg": [],
			"cs": [],
			"de": [],
			"el": [],
			"en": [],
			"es": [],
			"fr": [],
			"he": [],
			"hr": [],
			"hu": [],
			"it": [],
			"nl": [],
			"pl": [],
			"pt": [],
			"ro": [],
			"sk": [],
			"sl": [],
			"ua": [
				"Так. Кожен проєкт є незалежним і може бути переданий."
			]
		}
	},
	"agent-edit-code": {
		"audience": {
			"bg": "",
			"cs": "",
			"de": "",
			"el": "",
			"en": "",
			"es": "",
			"fr": "",
			"he": "",
			"hr": "",
			"hu": "",
			"it": "",
			"nl": "",
			"pl": "",
			"pt": "",
			"ro": "",
			"sk": "",
			"sl": "",
			"ua": "агент"
		},
		"question": {
			"bg": "",
			"cs": "",
			"de": "",
			"el": "",
			"en": "",
			"es": "",
			"fr": "",
			"he": "",
			"hr": "",
			"hu": "",
			"it": "",
			"nl": "",
			"pl": "",
			"pt": "",
			"ro": "",
			"sk": "",
			"sl": "",
			"ua": "Чи може клієнт самостійно редагувати код?"
		},
		"answer": {
			"bg": [],
			"cs": [],
			"de": [],
			"el": [],
			"en": [],
			"es": [],
			"fr": [],
			"he": [],
			"hr": [],
			"hu": [],
			"it": [],
			"nl": [],
			"pl": [],
			"pt": [],
			"ro": [],
			"sk": [],
			"sl": [],
			"ua": [
				"Не тоді, коли ми відповідаємо за проєкт.",
				"За потреби вони можуть співпрацювати через pull requests."
			]
		}
	},
	"agent-responsibility": {
		"audience": {
			"bg": "",
			"cs": "",
			"de": "",
			"el": "",
			"en": "",
			"es": "",
			"fr": "",
			"he": "",
			"hr": "",
			"hu": "",
			"it": "",
			"nl": "",
			"pl": "",
			"pt": "",
			"ro": "",
			"sk": "",
			"sl": "",
			"ua": "агент"
		},
		"question": {
			"bg": "",
			"cs": "",
			"de": "",
			"el": "",
			"en": "",
			"es": "",
			"fr": "",
			"he": "",
			"hr": "",
			"hu": "",
			"it": "",
			"nl": "",
			"pl": "",
			"pt": "",
			"ro": "",
			"sk": "",
			"sl": "",
			"ua": "Яка відповідальність агента?"
		},
		"answer": {
			"bg": [],
			"cs": [],
			"de": [],
			"el": [],
			"en": [],
			"es": [],
			"fr": [],
			"he": [],
			"hr": [],
			"hu": [],
			"it": [],
			"nl": [],
			"pl": [],
			"pt": [],
			"ro": [],
			"sk": [],
			"sl": [],
			"ua": [
				"Комунікувати з клієнтом.",
				"Презентувати продукт.",
				"Збирати запити.",
				"Перевіряти виконану роботу."
			]
		}
	},
	"agent-developer-responsibility": {
		"audience": {
			"bg": "",
			"cs": "",
			"de": "",
			"el": "",
			"en": "",
			"es": "",
			"fr": "",
			"he": "",
			"hr": "",
			"hu": "",
			"it": "",
			"nl": "",
			"pl": "",
			"pt": "",
			"ro": "",
			"sk": "",
			"sl": "",
			"ua": "агент"
		},
		"question": {
			"bg": "",
			"cs": "",
			"de": "",
			"el": "",
			"en": "",
			"es": "",
			"fr": "",
			"he": "",
			"hr": "",
			"hu": "",
			"it": "",
			"nl": "",
			"pl": "",
			"pt": "",
			"ro": "",
			"sk": "",
			"sl": "",
			"ua": "Яка відповідальність розробника?"
		},
		"answer": {
			"bg": [],
			"cs": [],
			"de": [],
			"el": [],
			"en": [],
			"es": [],
			"fr": [],
			"he": [],
			"hr": [],
			"hu": [],
			"it": [],
			"nl": [],
			"pl": [],
			"pt": [],
			"ro": [],
			"sk": [],
			"sl": [],
			"ua": [
				"Створювати функції.",
				"Виправляти помилки.",
				"Підтримувати систему."
			]
		}
	},
	"agent-controls-decisions": {
		"audience": {
			"bg": "",
			"cs": "",
			"de": "",
			"el": "",
			"en": "",
			"es": "",
			"fr": "",
			"he": "",
			"hr": "",
			"hu": "",
			"it": "",
			"nl": "",
			"pl": "",
			"pt": "",
			"ro": "",
			"sk": "",
			"sl": "",
			"ua": "агент"
		},
		"question": {
			"bg": "",
			"cs": "",
			"de": "",
			"el": "",
			"en": "",
			"es": "",
			"fr": "",
			"he": "",
			"hr": "",
			"hu": "",
			"it": "",
			"nl": "",
			"pl": "",
			"pt": "",
			"ro": "",
			"sk": "",
			"sl": "",
			"ua": "Хто контролює рішення?"
		},
		"answer": {
			"bg": [],
			"cs": [],
			"de": [],
			"el": [],
			"en": [],
			"es": [],
			"fr": [],
			"he": [],
			"hr": [],
			"hu": [],
			"it": [],
			"nl": [],
			"pl": [],
			"pt": [],
			"ro": [],
			"sk": [],
			"sl": [],
			"ua": [
				"Клієнт контролює бізнес-рішення.",
				"Агент контролює комунікацію та перевірку.",
				"Розробник контролює технічні рішення."
			]
		}
	},
	"agent-content": {
		"audience": {
			"bg": "",
			"cs": "",
			"de": "",
			"el": "",
			"en": "",
			"es": "",
			"fr": "",
			"he": "",
			"hr": "",
			"hu": "",
			"it": "",
			"nl": "",
			"pl": "",
			"pt": "",
			"ro": "",
			"sk": "",
			"sl": "",
			"ua": "агент"
		},
		"question": {
			"bg": "",
			"cs": "",
			"de": "",
			"el": "",
			"en": "",
			"es": "",
			"fr": "",
			"he": "",
			"hr": "",
			"hu": "",
			"it": "",
			"nl": "",
			"pl": "",
			"pt": "",
			"ro": "",
			"sk": "",
			"sl": "",
			"ua": "Чи надаємо ми контент?"
		},
		"answer": {
			"bg": [],
			"cs": [],
			"de": [],
			"el": [],
			"en": [],
			"es": [],
			"fr": [],
			"he": [],
			"hr": [],
			"hu": [],
			"it": [],
			"nl": [],
			"pl": [],
			"pt": [],
			"ro": [],
			"sk": [],
			"sl": [],
			"ua": [
				"Ми використовуємо контент клієнта, якщо він є.",
				"Якщо його немає, ми генеруємо базовий стартовий контент."
			]
		}
	},
	"agent-upsell": {
		"audience": {
			"bg": "",
			"cs": "",
			"de": "",
			"el": "",
			"en": "",
			"es": "",
			"fr": "",
			"he": "",
			"hr": "",
			"hu": "",
			"it": "",
			"nl": "",
			"pl": "",
			"pt": "",
			"ro": "",
			"sk": "",
			"sl": "",
			"ua": "агент"
		},
		"question": {
			"bg": "",
			"cs": "",
			"de": "",
			"el": "",
			"en": "",
			"es": "",
			"fr": "",
			"he": "",
			"hr": "",
			"hu": "",
			"it": "",
			"nl": "",
			"pl": "",
			"pt": "",
			"ro": "",
			"sk": "",
			"sl": "",
			"ua": "Чи можуть агенти робити додаткові продажі?"
		},
		"answer": {
			"bg": [],
			"cs": [],
			"de": [],
			"el": [],
			"en": [],
			"es": [],
			"fr": [],
			"he": [],
			"hr": [],
			"hu": [],
			"it": [],
			"nl": [],
			"pl": [],
			"pt": [],
			"ro": [],
			"sk": [],
			"sl": [],
			"ua": [
				"Так.",
				"Агенти можуть продавати додаткові функції, SMM-послуги та погодинну роботу розробника або агента."
			]
		}
	},
	"agent-white-label": {
		"audience": {
			"bg": "",
			"cs": "",
			"de": "",
			"el": "",
			"en": "",
			"es": "",
			"fr": "",
			"he": "",
			"hr": "",
			"hu": "",
			"it": "",
			"nl": "",
			"pl": "",
			"pt": "",
			"ro": "",
			"sk": "",
			"sl": "",
			"ua": "агент"
		},
		"question": {
			"bg": "",
			"cs": "",
			"de": "",
			"el": "",
			"en": "",
			"es": "",
			"fr": "",
			"he": "",
			"hr": "",
			"hu": "",
			"it": "",
			"nl": "",
			"pl": "",
			"pt": "",
			"ro": "",
			"sk": "",
			"sl": "",
			"ua": "Чи дозволяємо ми white-label?"
		},
		"answer": {
			"bg": [],
			"cs": [],
			"de": [],
			"el": [],
			"en": [],
			"es": [],
			"fr": [],
			"he": [],
			"hr": [],
			"hu": [],
			"it": [],
			"nl": [],
			"pl": [],
			"pt": [],
			"ro": [],
			"sk": [],
			"sl": [],
			"ua": [
				"Лише для бізнесів, з якими ми працюємо."
			]
		}
	},
	"agent-multilanguage": {
		"audience": {
			"bg": "",
			"cs": "",
			"de": "",
			"el": "",
			"en": "",
			"es": "",
			"fr": "",
			"he": "",
			"hr": "",
			"hu": "",
			"it": "",
			"nl": "",
			"pl": "",
			"pt": "",
			"ro": "",
			"sk": "",
			"sl": "",
			"ua": "агент"
		},
		"question": {
			"bg": "",
			"cs": "",
			"de": "",
			"el": "",
			"en": "",
			"es": "",
			"fr": "",
			"he": "",
			"hr": "",
			"hu": "",
			"it": "",
			"nl": "",
			"pl": "",
			"pt": "",
			"ro": "",
			"sk": "",
			"sl": "",
			"ua": "Чи підтримуємо ми кілька мов?"
		},
		"answer": {
			"bg": [],
			"cs": [],
			"de": [],
			"el": [],
			"en": [],
			"es": [],
			"fr": [],
			"he": [],
			"hr": [],
			"hu": [],
			"it": [],
			"nl": [],
			"pl": [],
			"pt": [],
			"ro": [],
			"sk": [],
			"sl": [],
			"ua": [
				"Так. Багатомовність підтримується за замовчуванням."
			]
		}
	},
	"agent-main-advantage": {
		"audience": {
			"bg": "",
			"cs": "",
			"de": "",
			"el": "",
			"en": "",
			"es": "",
			"fr": "",
			"he": "",
			"hr": "",
			"hu": "",
			"it": "",
			"nl": "",
			"pl": "",
			"pt": "",
			"ro": "",
			"sk": "",
			"sl": "",
			"ua": "агент"
		},
		"question": {
			"bg": "",
			"cs": "",
			"de": "",
			"el": "",
			"en": "",
			"es": "",
			"fr": "",
			"he": "",
			"hr": "",
			"hu": "",
			"it": "",
			"nl": "",
			"pl": "",
			"pt": "",
			"ro": "",
			"sk": "",
			"sl": "",
			"ua": "У чому наша головна перевага?"
		},
		"answer": {
			"bg": [],
			"cs": [],
			"de": [],
			"el": [],
			"en": [],
			"es": [],
			"fr": [],
			"he": [],
			"hr": [],
			"hu": [],
			"it": [],
			"nl": [],
			"pl": [],
			"pt": [],
			"ro": [],
			"sk": [],
			"sl": [],
			"ua": [
				"Ми спочатку створюємо, а потім продаємо.",
				"Ми справжні розробники, а не лише користувачі конструкторів.",
				"Ми пропонуємо швидкий запуск і безперервну підтримку."
			]
		}
	},
	"agent-if-business-says-no": {
		"audience": {
			"bg": "",
			"cs": "",
			"de": "",
			"el": "",
			"en": "",
			"es": "",
			"fr": "",
			"he": "",
			"hr": "",
			"hu": "",
			"it": "",
			"nl": "",
			"pl": "",
			"pt": "",
			"ro": "",
			"sk": "",
			"sl": "",
			"ua": "агент"
		},
		"question": {
			"bg": "",
			"cs": "",
			"de": "",
			"el": "",
			"en": "",
			"es": "",
			"fr": "",
			"he": "",
			"hr": "",
			"hu": "",
			"it": "",
			"nl": "",
			"pl": "",
			"pt": "",
			"ro": "",
			"sk": "",
			"sl": "",
			"ua": "Що робити, якщо бізнес зараз не зацікавлений?"
		},
		"answer": {
			"bg": [],
			"cs": [],
			"de": [],
			"el": [],
			"en": [],
			"es": [],
			"fr": [],
			"he": [],
			"hr": [],
			"hu": [],
			"it": [],
			"nl": [],
			"pl": [],
			"pt": [],
			"ro": [],
			"sk": [],
			"sl": [],
			"ua": [
				"Залиште короткий контакт, збережіть ввічливі відносини й рухайтеся далі.",
				"Мета - залишити двері відкритими для майбутнього контакту."
			]
		}
	},
	"developer-main-role": {
		"audience": {
			"bg": "",
			"cs": "",
			"de": "",
			"el": "",
			"en": "",
			"es": "",
			"fr": "",
			"he": "",
			"hr": "",
			"hu": "",
			"it": "",
			"nl": "",
			"pl": "",
			"pt": "",
			"ro": "",
			"sk": "",
			"sl": "",
			"ua": "розробник"
		},
		"question": {
			"bg": "",
			"cs": "",
			"de": "",
			"el": "",
			"en": "",
			"es": "",
			"fr": "",
			"he": "",
			"hr": "",
			"hu": "",
			"it": "",
			"nl": "",
			"pl": "",
			"pt": "",
			"ro": "",
			"sk": "",
			"sl": "",
			"ua": "Яка відповідальність розробника?"
		},
		"answer": {
			"bg": [],
			"cs": [],
			"de": [],
			"el": [],
			"en": [],
			"es": [],
			"fr": [],
			"he": [],
			"hr": [],
			"hu": [],
			"it": [],
			"nl": [],
			"pl": [],
			"pt": [],
			"ro": [],
			"sk": [],
			"sl": [],
			"ua": [
				"Створювати затверджені функції.",
				"Виправляти погоджені помилки.",
				"Підтримувати технічну якість і стабільність."
			]
		}
	},
	"developer-bug-definition": {
		"audience": {
			"bg": "",
			"cs": "",
			"de": "",
			"el": "",
			"en": "",
			"es": "",
			"fr": "",
			"he": "",
			"hr": "",
			"hu": "",
			"it": "",
			"nl": "",
			"pl": "",
			"pt": "",
			"ro": "",
			"sk": "",
			"sl": "",
			"ua": "розробник"
		},
		"question": {
			"bg": "",
			"cs": "",
			"de": "",
			"el": "",
			"en": "",
			"es": "",
			"fr": "",
			"he": "",
			"hr": "",
			"hu": "",
			"it": "",
			"nl": "",
			"pl": "",
			"pt": "",
			"ro": "",
			"sk": "",
			"sl": "",
			"ua": "Що вважається помилкою?"
		},
		"answer": {
			"bg": [],
			"cs": [],
			"de": [],
			"el": [],
			"en": [],
			"es": [],
			"fr": [],
			"he": [],
			"hr": [],
			"hu": [],
			"it": [],
			"nl": [],
			"pl": [],
			"pt": [],
			"ro": [],
			"sk": [],
			"sl": [],
			"ua": [
				"Якщо щось не працює так, як було спочатку погоджено або описано, це помилка, яку слід виправити без оплати як за нову функцію."
			]
		}
	},
	"developer-paid-request": {
		"audience": {
			"bg": "",
			"cs": "",
			"de": "",
			"el": "",
			"en": "",
			"es": "",
			"fr": "",
			"he": "",
			"hr": "",
			"hu": "",
			"it": "",
			"nl": "",
			"pl": "",
			"pt": "",
			"ro": "",
			"sk": "",
			"sl": "",
			"ua": "розробник"
		},
		"question": {
			"bg": "",
			"cs": "",
			"de": "",
			"el": "",
			"en": "",
			"es": "",
			"fr": "",
			"he": "",
			"hr": "",
			"hu": "",
			"it": "",
			"nl": "",
			"pl": "",
			"pt": "",
			"ro": "",
			"sk": "",
			"sl": "",
			"ua": "Що вважається платним запитом?"
		},
		"answer": {
			"bg": [],
			"cs": [],
			"de": [],
			"el": [],
			"en": [],
			"es": [],
			"fr": [],
			"he": [],
			"hr": [],
			"hu": [],
			"it": [],
			"nl": [],
			"pl": [],
			"pt": [],
			"ro": [],
			"sk": [],
			"sl": [],
			"ua": [
				"Будь-яка нова функція, редизайн або зміна обсягу робіт поза початковою домовленістю."
			]
		}
	},
	"developer-scope-change": {
		"audience": {
			"bg": "",
			"cs": "",
			"de": "",
			"el": "",
			"en": "",
			"es": "",
			"fr": "",
			"he": "",
			"hr": "",
			"hu": "",
			"it": "",
			"nl": "",
			"pl": "",
			"pt": "",
			"ro": "",
			"sk": "",
			"sl": "",
			"ua": "розробник"
		},
		"question": {
			"bg": "",
			"cs": "",
			"de": "",
			"el": "",
			"en": "",
			"es": "",
			"fr": "",
			"he": "",
			"hr": "",
			"hu": "",
			"it": "",
			"nl": "",
			"pl": "",
			"pt": "",
			"ro": "",
			"sk": "",
			"sl": "",
			"ua": "Що робити, якщо клієнт змінює вимоги під час розробки?"
		},
		"answer": {
			"bg": [],
			"cs": [],
			"de": [],
			"el": [],
			"en": [],
			"es": [],
			"fr": [],
			"he": [],
			"hr": [],
			"hu": [],
			"it": [],
			"nl": [],
			"pl": [],
			"pt": [],
			"ro": [],
			"sk": [],
			"sl": [],
			"ua": [
				"Призупинити реалізацію.",
				"Попросити повторну оцінку через агента.",
				"Продовжувати лише після оновленого затвердження."
			]
		}
	},
	"developer-task-finish": {
		"audience": {
			"bg": "",
			"cs": "",
			"de": "",
			"el": "",
			"en": "",
			"es": "",
			"fr": "",
			"he": "",
			"hr": "",
			"hu": "",
			"it": "",
			"nl": "",
			"pl": "",
			"pt": "",
			"ro": "",
			"sk": "",
			"sl": "",
			"ua": "розробник"
		},
		"question": {
			"bg": "",
			"cs": "",
			"de": "",
			"el": "",
			"en": "",
			"es": "",
			"fr": "",
			"he": "",
			"hr": "",
			"hu": "",
			"it": "",
			"nl": "",
			"pl": "",
			"pt": "",
			"ro": "",
			"sk": "",
			"sl": "",
			"ua": "Коли завдання вважається виконаним?"
		},
		"answer": {
			"bg": [],
			"cs": [],
			"de": [],
			"el": [],
			"en": [],
			"es": [],
			"fr": [],
			"he": [],
			"hr": [],
			"hu": [],
			"it": [],
			"nl": [],
			"pl": [],
			"pt": [],
			"ro": [],
			"sk": [],
			"sl": [],
			"ua": [
				"Спочатку розробник позначає його виконаним.",
				"Потім агент перевіряє його.",
				"Нарешті клієнт затверджує його."
			]
		}
	},
	"developer-priority": {
		"audience": {
			"bg": "",
			"cs": "",
			"de": "",
			"el": "",
			"en": "",
			"es": "",
			"fr": "",
			"he": "",
			"hr": "",
			"hu": "",
			"it": "",
			"nl": "",
			"pl": "",
			"pt": "",
			"ro": "",
			"sk": "",
			"sl": "",
			"ua": "розробник"
		},
		"question": {
			"bg": "",
			"cs": "",
			"de": "",
			"el": "",
			"en": "",
			"es": "",
			"fr": "",
			"he": "",
			"hr": "",
			"hu": "",
			"it": "",
			"nl": "",
			"pl": "",
			"pt": "",
			"ro": "",
			"sk": "",
			"sl": "",
			"ua": "Чи можуть кілька клієнтських запитів виконуватися одночасно?"
		},
		"answer": {
			"bg": [],
			"cs": [],
			"de": [],
			"el": [],
			"en": [],
			"es": [],
			"fr": [],
			"he": [],
			"hr": [],
			"hu": [],
			"it": [],
			"nl": [],
			"pl": [],
			"pt": [],
			"ro": [],
			"sk": [],
			"sl": [],
			"ua": [
				"Так, але кожен запит зберігає власну позицію в черзі, оцінку та пріоритет."
			]
		}
	},
	"developer-client-code-access": {
		"audience": {
			"bg": "",
			"cs": "",
			"de": "",
			"el": "",
			"en": "",
			"es": "",
			"fr": "",
			"he": "",
			"hr": "",
			"hu": "",
			"it": "",
			"nl": "",
			"pl": "",
			"pt": "",
			"ro": "",
			"sk": "",
			"sl": "",
			"ua": "розробник"
		},
		"question": {
			"bg": "",
			"cs": "",
			"de": "",
			"el": "",
			"en": "",
			"es": "",
			"fr": "",
			"he": "",
			"hr": "",
			"hu": "",
			"it": "",
			"nl": "",
			"pl": "",
			"pt": "",
			"ro": "",
			"sk": "",
			"sl": "",
			"ua": "Чи може клієнт редагувати код напряму?"
		},
		"answer": {
			"bg": [],
			"cs": [],
			"de": [],
			"el": [],
			"en": [],
			"es": [],
			"fr": [],
			"he": [],
			"hr": [],
			"hu": [],
			"it": [],
			"nl": [],
			"pl": [],
			"pt": [],
			"ro": [],
			"sk": [],
			"sl": [],
			"ua": [
				"Не тоді, коли ми відповідаємо за проєкт.",
				"За потреби співпраця може відбуватися через pull requests."
			]
		}
	},
	"developer-hosting": {
		"audience": {
			"bg": "",
			"cs": "",
			"de": "",
			"el": "",
			"en": "",
			"es": "",
			"fr": "",
			"he": "",
			"hr": "",
			"hu": "",
			"it": "",
			"nl": "",
			"pl": "",
			"pt": "",
			"ro": "",
			"sk": "",
			"sl": "",
			"ua": "розробник"
		},
		"question": {
			"bg": "",
			"cs": "",
			"de": "",
			"el": "",
			"en": "",
			"es": "",
			"fr": "",
			"he": "",
			"hr": "",
			"hu": "",
			"it": "",
			"nl": "",
			"pl": "",
			"pt": "",
			"ro": "",
			"sk": "",
			"sl": "",
			"ua": "Де розміщуються проєкти?"
		},
		"answer": {
			"bg": [],
			"cs": [],
			"de": [],
			"el": [],
			"en": [],
			"es": [],
			"fr": [],
			"he": [],
			"hr": [],
			"hu": [],
			"it": [],
			"nl": [],
			"pl": [],
			"pt": [],
			"ro": [],
			"sk": [],
			"sl": [],
			"ua": [
				"Проєкти можуть розміщуватися на GitHub Pages або в іншого провайдера, обраного для клієнта."
			]
		}
	},
	"developer-ownership": {
		"audience": {
			"bg": "",
			"cs": "",
			"de": "",
			"el": "",
			"en": "",
			"es": "",
			"fr": "",
			"he": "",
			"hr": "",
			"hu": "",
			"it": "",
			"nl": "",
			"pl": "",
			"pt": "",
			"ro": "",
			"sk": "",
			"sl": "",
			"ua": "розробник"
		},
		"question": {
			"bg": "",
			"cs": "",
			"de": "",
			"el": "",
			"en": "",
			"es": "",
			"fr": "",
			"he": "",
			"hr": "",
			"hu": "",
			"it": "",
			"nl": "",
			"pl": "",
			"pt": "",
			"ro": "",
			"sk": "",
			"sl": "",
			"ua": "Чи може клієнт забрати сайт і піти?"
		},
		"answer": {
			"bg": [],
			"cs": [],
			"de": [],
			"el": [],
			"en": [],
			"es": [],
			"fr": [],
			"he": [],
			"hr": [],
			"hu": [],
			"it": [],
			"nl": [],
			"pl": [],
			"pt": [],
			"ro": [],
			"sk": [],
			"sl": [],
			"ua": [
				"Так. Кожен проєкт є незалежним і може бути переданий відповідно до домовленості."
			]
		}
	},
	"developer-content": {
		"audience": {
			"bg": "",
			"cs": "",
			"de": "",
			"el": "",
			"en": "",
			"es": "",
			"fr": "",
			"he": "",
			"hr": "",
			"hu": "",
			"it": "",
			"nl": "",
			"pl": "",
			"pt": "",
			"ro": "",
			"sk": "",
			"sl": "",
			"ua": "розробник"
		},
		"question": {
			"bg": "",
			"cs": "",
			"de": "",
			"el": "",
			"en": "",
			"es": "",
			"fr": "",
			"he": "",
			"hr": "",
			"hu": "",
			"it": "",
			"nl": "",
			"pl": "",
			"pt": "",
			"ro": "",
			"sk": "",
			"sl": "",
			"ua": "Хто надає тексти та зображення?"
		},
		"answer": {
			"bg": [],
			"cs": [],
			"de": [],
			"el": [],
			"en": [],
			"es": [],
			"fr": [],
			"he": [],
			"hr": [],
			"hu": [],
			"it": [],
			"nl": [],
			"pl": [],
			"pt": [],
			"ro": [],
			"sk": [],
			"sl": [],
			"ua": [
				"Надавайте перевагу контенту клієнта, якщо він є.",
				"Якщо його немає, використовуйте згенерований базовий стартовий контент для запуску."
			]
		}
	},
	"developer-decisions": {
		"audience": {
			"bg": "",
			"cs": "",
			"de": "",
			"el": "",
			"en": "",
			"es": "",
			"fr": "",
			"he": "",
			"hr": "",
			"hu": "",
			"it": "",
			"nl": "",
			"pl": "",
			"pt": "",
			"ro": "",
			"sk": "",
			"sl": "",
			"ua": "розробник"
		},
		"question": {
			"bg": "",
			"cs": "",
			"de": "",
			"el": "",
			"en": "",
			"es": "",
			"fr": "",
			"he": "",
			"hr": "",
			"hu": "",
			"it": "",
			"nl": "",
			"pl": "",
			"pt": "",
			"ro": "",
			"sk": "",
			"sl": "",
			"ua": "Хто контролює рішення?"
		},
		"answer": {
			"bg": [],
			"cs": [],
			"de": [],
			"el": [],
			"en": [],
			"es": [],
			"fr": [],
			"he": [],
			"hr": [],
			"hu": [],
			"it": [],
			"nl": [],
			"pl": [],
			"pt": [],
			"ro": [],
			"sk": [],
			"sl": [],
			"ua": [
				"Клієнт контролює бізнес-рішення.",
				"Агент контролює комунікацію та перевірку.",
				"Розробник контролює рішення щодо технічної реалізації."
			]
		}
	},
	"developer-delay": {
		"audience": {
			"bg": "",
			"cs": "",
			"de": "",
			"el": "",
			"en": "",
			"es": "",
			"fr": "",
			"he": "",
			"hr": "",
			"hu": "",
			"it": "",
			"nl": "",
			"pl": "",
			"pt": "",
			"ro": "",
			"sk": "",
			"sl": "",
			"ua": "розробник"
		},
		"question": {
			"bg": "",
			"cs": "",
			"de": "",
			"el": "",
			"en": "",
			"es": "",
			"fr": "",
			"he": "",
			"hr": "",
			"hu": "",
			"it": "",
			"nl": "",
			"pl": "",
			"pt": "",
			"ro": "",
			"sk": "",
			"sl": "",
			"ua": "Що робити, якщо оцінка стає неточною?"
		},
		"answer": {
			"bg": [],
			"cs": [],
			"de": [],
			"el": [],
			"en": [],
			"es": [],
			"fr": [],
			"he": [],
			"hr": [],
			"hu": [],
			"it": [],
			"nl": [],
			"pl": [],
			"pt": [],
			"ro": [],
			"sk": [],
			"sl": [],
			"ua": [
				"Повідомте про це завчасно через агента.",
				"Терміни мають бути скориговані або запит має бути переоцінений."
			]
		}
	},
	"developer-no-direct-scope": {
		"audience": {
			"bg": "",
			"cs": "",
			"de": "",
			"el": "",
			"en": "",
			"es": "",
			"fr": "",
			"he": "",
			"hr": "",
			"hu": "",
			"it": "",
			"nl": "",
			"pl": "",
			"pt": "",
			"ro": "",
			"sk": "",
			"sl": "",
			"ua": "розробник"
		},
		"question": {
			"bg": "",
			"cs": "",
			"de": "",
			"el": "",
			"en": "",
			"es": "",
			"fr": "",
			"he": "",
			"hr": "",
			"hu": "",
			"it": "",
			"nl": "",
			"pl": "",
			"pt": "",
			"ro": "",
			"sk": "",
			"sl": "",
			"ua": "Чи мають розробники напряму погоджувати зміни бізнес-обсягу з клієнтом?"
		},
		"answer": {
			"bg": [],
			"cs": [],
			"de": [],
			"el": [],
			"en": [],
			"es": [],
			"fr": [],
			"he": [],
			"hr": [],
			"hu": [],
			"it": [],
			"nl": [],
			"pl": [],
			"pt": [],
			"ro": [],
			"sk": [],
			"sl": [],
			"ua": [
				"Ні.",
				"Обсяг робіт, ціна та перевірка мають проходити через агентський процес."
			]
		}
	},
	"developer-quality": {
		"audience": {
			"bg": "",
			"cs": "",
			"de": "",
			"el": "",
			"en": "",
			"es": "",
			"fr": "",
			"he": "",
			"hr": "",
			"hu": "",
			"it": "",
			"nl": "",
			"pl": "",
			"pt": "",
			"ro": "",
			"sk": "",
			"sl": "",
			"ua": "розробник"
		},
		"question": {
			"bg": "",
			"cs": "",
			"de": "",
			"el": "",
			"en": "",
			"es": "",
			"fr": "",
			"he": "",
			"hr": "",
			"hu": "",
			"it": "",
			"nl": "",
			"pl": "",
			"pt": "",
			"ro": "",
			"sk": "",
			"sl": "",
			"ua": "Що очікується перед позначенням роботи виконаною?"
		},
		"answer": {
			"bg": [],
			"cs": [],
			"de": [],
			"el": [],
			"en": [],
			"es": [],
			"fr": [],
			"he": [],
			"hr": [],
			"hu": [],
			"it": [],
			"nl": [],
			"pl": [],
			"pt": [],
			"ro": [],
			"sk": [],
			"sl": [],
			"ua": [
				"Функція має працювати, бути перевіреною розробником і готовою до перевірки агентом."
			]
		}
	},
	"developer-small-fixes": {
		"audience": {
			"bg": "",
			"cs": "",
			"de": "",
			"el": "",
			"en": "",
			"es": "",
			"fr": "",
			"he": "",
			"hr": "",
			"hu": "",
			"it": "",
			"nl": "",
			"pl": "",
			"pt": "",
			"ro": "",
			"sk": "",
			"sl": "",
			"ua": "розробник"
		},
		"question": {
			"bg": "",
			"cs": "",
			"de": "",
			"el": "",
			"en": "",
			"es": "",
			"fr": "",
			"he": "",
			"hr": "",
			"hu": "",
			"it": "",
			"nl": "",
			"pl": "",
			"pt": "",
			"ro": "",
			"sk": "",
			"sl": "",
			"ua": "Чи слід автоматично додавати невеликі незатверджені покращення?"
		},
		"answer": {
			"bg": [],
			"cs": [],
			"de": [],
			"el": [],
			"en": [],
			"es": [],
			"fr": [],
			"he": [],
			"hr": [],
			"hu": [],
			"it": [],
			"nl": [],
			"pl": [],
			"pt": [],
			"ro": [],
			"sk": [],
			"sl": [],
			"ua": [
				"Лише якщо вони очевидно корисні, малоризикові та не змінюють погоджений обсяг робіт.",
				"Інакше їх слід спочатку запропонувати."
			]
		}
	}
}
